{
  "version": "7",
  "dialect": "sqlite",
  "entries": [
    {
      "idx": 0,
      "version": "6",
      "when": 1784184784363,
      "tag": "0000_short_umar",
      "breakpoints": true
    },
    {
      "idx": 1,
      "version": "6",
      "when": 1784218014773,
      "tag": "0001_lovely_blazing_skull",
      "breakpoints": true
    },
    {
      "idx": 2,
      "version": "6",
      "when": 1784224253238,
      "tag": "0002_reflective_mantis",
      "breakpoints": true
    },
    {
      "idx": 3,
      "version": "6",
      "when": 1784782655135,
      "tag": "0003_bent_gamora",
      "breakpoints": true
    }
  ]
}